{
  "name": "webcomponentsjs",
  "main": "webcomponents.js",
  "homepage": "http://webcomponents.org",
  "authors": [
    "The Polymer Authors"
  ],
  "keywords": [
    "webcomponents"
  ],
  "license": "BSD",
  "ignore": [],
  "_release": "c04390b334",
  "_resolution": {
    "type": "branch",
    "branch": "master",
    "commit": "c04390b3341484139a36b5b38d02d925ca79a85e"
  },
  "_source": "git://github.com/Polymer/webcomponentsjs.git",
  "_target": "master",
  "_originalSource": "Polymer/webcomponentsjs"
}